qtbplot/__init__.py
qtbplot/colors.py
qtbplot/plot.py
qtb_plot-0.3.58.dist-info/WHEEL
qtb_plot-0.3.58.dist-info/METADATA
qtb_plot-0.3.58.dist-info/RECORD
