Metadata-Version: 2.1
Name: qtb-plot
Version: 0.3.58
Summary: Standard plotting styles of our institute
Home-page: https://gitlab.com/marvin.vanaalst/qtb-plot
License: GPL-4
Keywords: plotting
Author: Marvin van Aalst
Author-email: marvin.vanaalst@gmail.com
Requires-Python: >=3.8,<4.0
Classifier: License :: Other/Proprietary License
Classifier: Programming Language :: Python :: 3
Classifier: Programming Language :: Python :: 3.8
Classifier: Programming Language :: Python :: 3.9
Classifier: Programming Language :: Python :: 3.10
Classifier: Programming Language :: Python :: 3.11
Requires-Dist: matplotlib (>=3.6.0,<4.0.0)
Project-URL: Repository, https://gitlab.com/marvin.vanaalst/qtb-plot
